argos/__init__.py
argos/annotate.py
argos/batch_motion_track.py
argos/batchtrack.py
argos/batchtrack_queue.py
argos/breeze_resources.py
argos/capture.py
argos/capture.updated.py
argos/caputil.py
argos/ccapture.cp311-win_amd64.pyd
argos/constants.py
argos/convert_dlc.py
argos/csrtracker.py
argos/cutility.cp311-win_amd64.pyd
argos/extract_frames.py
argos/frameview.py
argos/limitswidget.py
argos/plot_tracks.py
argos/plotutil.py
argos/review.py
argos/segment.py
argos/segwidget.py
argos/sortracker.py
argos/sortrackerwidget.py
argos/test_ccap.py
argos/test_tracker.py
argos/track.py
argos/tracklist.py
argos/trackreader.py
argos/trackview.py
argos/utility.py
argos/vreader.py
argos/vwidget.py
argos/writer.py
argos/yolactwidget.py
yolact/__init__.py
yolact/backbone.py
yolact/evaluate.py
yolact/run_coco_eval.py
yolact/train.py
yolact/yolact.py
yolact/yolact_.py
yolact/data/__init__.py
yolact/data/coco.py
yolact/data/config.py
yolact/data/config_20200305.py
yolact/data/scripts/__init__.py
yolact/data/scripts/mix_sets.py
yolact/external/__init__.py
yolact/external/DCNv2/__init__.py
yolact/external/DCNv2/dcn_v2.py
yolact/external/DCNv2/setup.py
yolact/external/DCNv2/test.py
yolact/layers/__init__.py
yolact/layers/box_utils.py
yolact/layers/interpolate.py
yolact/layers/output_utils.py
yolact/layers/functions/__init__.py
yolact/layers/functions/detection.py
yolact/layers/modules/__init__.py
yolact/layers/modules/multibox_loss.py
yolact/scripts/__init__.py
yolact/scripts/augment_bbox.py
yolact/scripts/bbox_recall.py
yolact/scripts/cluster_bbox_sizes.py
yolact/scripts/compute_masks.py
yolact/scripts/convert_darknet.py
yolact/scripts/convert_sbd.py
yolact/scripts/make_grid.py
yolact/scripts/optimize_bboxes.py
yolact/scripts/parse_eval.py
yolact/scripts/plot_loss.py
yolact/scripts/save_bboxes.py
yolact/scripts/unpack_statedict.py
yolact/utils/__init__.py
yolact/utils/augmentations.py
yolact/utils/cython_nms.cp311-win_amd64.pyd
yolact/utils/functions.py
yolact/utils/logger.py
argos_toolkit-0.2.0.dist-info/LICENSE
argos_toolkit-0.2.0.dist-info/LICENSE.txt
argos_toolkit-0.2.0.dist-info/METADATA
argos_toolkit-0.2.0.dist-info/WHEEL
argos_toolkit-0.2.0.dist-info/top_level.txt
argos_toolkit-0.2.0.dist-info/RECORD
