Metadata-Version: 2.1
Name: argos_toolkit
Version: 0.2.0
Summary: Software tools to facilitate tracking multiple objects (animals) in a video.
Home-page: https://github.com/subhacom/argos
Author: Subhasis Ray
Author-email: ray.subhasis@gmail.com
Project-URL: Documentation, https://argos.readthedocs.io
Project-URL: Source, https://github.com/subhacom/argos
Project-URL: Tracker, https://github.com/subhacom/argos/issues
Classifier: Programming Language :: Python :: 3
Classifier: License :: OSI Approved :: GNU General Public License (GPL)
Classifier: Operating System :: Microsoft :: Windows
Classifier: Operating System :: MacOS
Classifier: Operating System :: POSIX :: Linux
Classifier: Topic :: Scientific/Engineering
Classifier: Topic :: Utilities
Requires-Python: >=3.6
License-File: LICENSE
License-File: LICENSE.txt
Requires-Dist: cython
Requires-Dist: torch
Requires-Dist: torchvision
Requires-Dist: numpy
Requires-Dist: scipy
Requires-Dist: scikit-learn
Requires-Dist: pandas
Requires-Dist: tables
Requires-Dist: sortedcontainers
Requires-Dist: pyqt5
Requires-Dist: opencv-contrib-python
Requires-Dist: pyyaml
Requires-Dist: matplotlib
Requires-Dist: qdarkstyle
